IO/output_unit.v
`timescale 1ns/1ns

// Output Unit - afișează valori în terminal (decimal, 16 biți)
// Protocol: CU trimite out_req=1 + out_data, Output Unit afișează și răspunde cu out_ack=1

module output_unit #(
    parameter DW = 16
)(
    input               clk,
    input               rst_b,
    input               out_req,    // request de la CU
    input      [DW-1:0] out_data,   // valoarea de afișat
    output reg          out_ack     // acknowledge către CU
);

    // State machine
    localparam IDLE = 2'b00;
    localparam WRITE = 2'b01;
    localparam DONE = 2'b10;
    
    reg [1:0] state;

    // FSM pentru afișare
    always @(posedge clk or negedge rst_b) begin
        if (!rst_b) begin
            state <= IDLE;
            out_ack <= 1'b0;
        end
        else begin
            case (state)
                IDLE: begin
                    out_ack <= 1'b0;
                    if (out_req) begin
                        state <= WRITE;
                    end
                end
                
                WRITE: begin
                    // Afișează în terminal
                    $display("[OUTPUT_UNIT] OUT> %0d", out_data);
                    state <= DONE;
                end
                
                DONE: begin
                    out_ack <= 1'b1;
                    if (!out_req) begin
                        // CU a văzut ack-ul și a dezactivat req
                        out_ack <= 1'b0;
                        state <= IDLE;
                    end
                end
                
                default: state <= IDLE;
            endcase
        end
    end

endmodule

IO/input_unit.v
`timescale 1ns/1ns

// Input Unit - citește valori de la stdin (decimal, 16 biți)
// Protocol: CU trimite inp_req=1, Input Unit citește și răspunde cu inp_ack=1

module input_unit #(
    parameter DW = 16
)(
    input               clk,
    input               rst_b,
    input               inp_req,    // request de la CU
    output reg [DW-1:0] inp_data,   // valoarea citită
    output reg          inp_ack     // acknowledge către CU
);

    // State machine
    localparam IDLE = 2'b00;
    localparam READ = 2'b01;
    localparam DONE = 2'b10;
    
    reg [1:0] state;
    reg [DW-1:0] temp_data;
    integer scan_result;

    // FSM pentru citire
    always @(posedge clk or negedge rst_b) begin
        if (!rst_b) begin
            state <= IDLE;
            inp_data <= {DW{1'b0}};
            inp_ack <= 1'b0;
        end
        else begin
            case (state)
                IDLE: begin
                    inp_ack <= 1'b0;
                    if (inp_req)
                        state <= READ;
                end
                
                READ: begin
                    // Citește de la stdin (blocking)
                    $display("[INP] Introdu o valoare (decimal): ");
                    scan_result = $fscanf(32'h8000_0000, "%d", temp_data);
                    inp_data <= temp_data;
                    $display("[INP] Citit: %0d (0x%h)", temp_data, temp_data);
                    state <= DONE;
                end
                
                DONE: begin
                    inp_ack <= 1'b1;
                    if (!inp_req) begin
                        inp_ack <= 1'b0;
                        state <= IDLE;
                    end
                end
                
                default: state <= IDLE;
            endcase
        end
    end

endmodule

IO/io_tb.v
`timescale 1ns/1ns

// Testbench pentru Input Unit și Output Unit
// Simulează comportamentul CU-ului: trimite req, așteaptă ack

`include "input_unit.v"
`include "output_unit.v"

module io_tb;
    reg clk;
    reg rst_b;
    
    // Semnale Input Unit
    reg inp_req;
    wire [15:0] inp_data;
    wire inp_ack;
    
    // Semnale Output Unit
    reg out_req;
    reg [15:0] out_data;
    wire out_ack;
    
    // Instanțiere Input Unit (fără fișier = stdin)
    input_unit #(
        .DW(16)
    ) inp (
        .clk(clk),
        .rst_b(rst_b),
        .inp_req(inp_req),
        .inp_data(inp_data),
        .inp_ack(inp_ack)
    );
    
    // Instanțiere Output Unit
    output_unit #(
        .DW(16)
    ) outp (
        .clk(clk),
        .rst_b(rst_b),
        .out_req(out_req),
        .out_data(out_data),
        .out_ack(out_ack)
    );
    
    // Clock generation
    initial clk = 0;
    always #50 clk = ~clk;  // 100ns perioadă
    
    // Task pentru a simula un INP request (ca CU-ul)
    task do_input;
        output [15:0] value;
        begin
            $display("\n[TB] === INP Request ===");
            @(posedge clk);
            inp_req <= 1'b1;
            
            // Așteaptă ack
            wait(inp_ack == 1'b1);
            @(posedge clk);
            value = inp_data;
            $display("[TB] Primit: %0d (0x%h)", inp_data, inp_data);
            
            // Dezactivează req
            inp_req <= 1'b0;
            
            // Așteaptă ack să cadă
            wait(inp_ack == 1'b0);
            @(posedge clk);
            $display("[TB] INP complet\n");
        end
    endtask
    
    // Task pentru a simula un OUT request (ca CU-ul)
    task do_output;
        input [15:0] value;
        begin
            $display("\n[TB] === OUT Request: %0d ===", value);
            @(posedge clk);
            out_data <= value;
            out_req <= 1'b1;
            
            // Așteaptă ack
            wait(out_ack == 1'b1);
            @(posedge clk);
            
            // Dezactivează req
            out_req <= 1'b0;
            
            // Așteaptă ack să cadă
            wait(out_ack == 1'b0);
            @(posedge clk);
            $display("[TB] OUT complet\n");
        end
    endtask
    
    // Variabilă pentru valoarea citită
    reg [15:0] read_value;
    
    // Test scenario
    initial begin
        $dumpfile("io_dump.vcd");
        $dumpvars(0, io_tb);
        
        // Inițializare
        rst_b = 0;
        inp_req = 0;
        out_req = 0;
        out_data = 0;
        
        // Reset
        #200;
        rst_b = 1;
        #100;
        
        $display("========================================");
        $display("    Test I/O Units - Mod Interactiv    ");
        $display("========================================\n");
        
        // Test 1: Citește o valoare de la utilizator
        $display("Test 1: Citire de la utilizator");
        do_input(read_value);
        $display("[TB] Valoare stocată: %0d", read_value);
        
        // Test 2: Afișează valoarea citită
        $display("Test 2: Afișare valoare citită");
        do_output(read_value);
        
        // Test 3: Afișează o valoare fixă
        $display("Test 3: Afișare valoare fixă (12345)");
        do_output(16'd12345);
        
        // Test 4: Citește altă valoare
        $display("Test 4: A doua citire");
        do_input(read_value);
        
        // Test 5: Afișează noua valoare
        $display("Test 5: Afișare a doua valoare");
        do_output(read_value);
        
        #500;
        $display("\n========================================");
        $display("         Test I/O Complet!              ");
        $display("========================================");
        $finish;
    end

endmodule

IO/tb/io_dump.vcd
$date
	Thu Dec  4 16:35:26 2025
$end
$version
	Icarus Verilog
$end
$timescale
	1ns
$end
$scope module io_tb $end
$var wire 1 ! out_ack $end
$var wire 16 " inp_data [15:0] $end
$var wire 1 # inp_ack $end
$var reg 1 $ clk $end
$var reg 1 % inp_req $end
$var reg 16 & out_data [15:0] $end
$var reg 1 ' out_req $end
$var reg 16 ( read_value [15:0] $end
$var reg 1 ) rst_b $end
$scope module inp $end
$var wire 1 $ clk $end
$var wire 1 % inp_req $end
$var wire 1 ) rst_b $end
$var parameter 2 * DONE $end
$var parameter 32 + DW $end
$var parameter 2 , IDLE $end
$var parameter 2 - READ $end
$var reg 1 # inp_ack $end
$var reg 16 . inp_data [15:0] $end
$var reg 2 / state [1:0] $end
$var reg 16 0 temp_data [15:0] $end
$var integer 32 1 scan_result [31:0] $end
$upscope $end
$scope module outp $end
$var wire 1 $ clk $end
$var wire 16 2 out_data [15:0] $end
$var wire 1 ' out_req $end
$var wire 1 ) rst_b $end
$var parameter 2 3 DONE $end
$var parameter 32 4 DW $end
$var parameter 2 5 IDLE $end
$var parameter 2 6 WRITE $end
$var reg 1 ! out_ack $end
$var reg 2 7 state [1:0] $end
$upscope $end
$scope task do_input $end
$var reg 16 8 value [15:0] $end
$upscope $end
$scope task do_output $end
$var reg 16 9 value [15:0] $end
$upscope $end
$upscope $end
$enddefinitions $end
$comment Show the parameter values. $end
$dumpall
b1 6
b0 5
b10000 4
b10 3
b1 -
b0 ,
b10000 +
b10 *
$end
#0
$dumpvars
bx 9
bx 8
b0 7
b0 2
bx 1
bx 0
b0 /
b0 .
0)
bx (
0'
b0 &
0%
0$
0#
b0 "
0!
$end
#50
1$
#100
0$
#150
1$
#200
0$
1)
#250
1$
#300
0$
#350
1%
1$
#400
0$
#450
b1 /
1$
#500
0$
#550
b10 /
b10100 "
b10100 .
b1 1
b10100 0
1$
#600
0$
#650
1#
1$
#700
0$
#750
0%
b10100 8
1$
#800
0$
#850
b0 /
0#
1$
#900
0$
#950
b10100 9
b10100 (
1$
#1000
0$
#1050
1'
b10100 &
b10100 2
1$
#1100
0$
#1150
b1 7
1$
#1200
0$
#1250
b10 7
1$
#1300
0$
#1350
1!
1$
#1400
0$
#1450
0'
1$
#1500
0$
#1550
b0 7
0!
1$
#1600
0$
#1650
b11000000111001 9
1$
#1700
0$
#1750
1'
b11000000111001 &
b11000000111001 2
1$
#1800
0$
#1850
b1 7
1$
#1900
0$
#1950
b10 7
1$
#2000
0$
#2050
1!
1$
#2100
0$
#2150
0'
1$
#2200
0$
#2250
b0 7
0!
1$
#2300
0$
#2350
1$
#2400
0$
#2450
1%
1$
#2500
0$
#2550
b1 /
1$
#2600
0$
#2650
b10 /
b11110 "
b11110 .
b11110 0
1$
#2700
0$
#2750
1#
1$
#2800
0$
#2850
0%
b11110 8
1$
#2900
0$
#2950
b0 /
0#
1$
#3000
0$
#3050
b11110 9
b11110 (
1$
#3100
0$
#3150
1'
b11110 &
b11110 2
1$
#3200
0$
#3250
b1 7
1$
#3300
0$
#3350
b10 7
1$
#3400
0$
#3450
1!
1$
#3500
0$
#3550
0'
1$
#3600
0$
#3650
b0 7
0!
1$
