Memory/memory_512x16.v
module memory_512x16 #(
    parameter AW = 9,          // address width (512 = 2^9)
    parameter DW = 16,         // data width
    parameter INIT_FILE = ""   // optional: mem init (hex/binary)
)(
    input               clk,
    input               rst_b,
    input               write,      // write enable (active high)
    input               read,       // read enable  (active high)
    input  [AW-1:0]     addr,       // address
    input  [DW-1:0]     din,        // data in
    output reg [DW-1:0] dout        // data out
);

    reg [DW-1:0] mem [0:(1 << AW)-1];

    // Optional initialization
    integer i;
    initial begin
        for (i = 0; i < (1 << AW); i = i + 1)
                mem[i] = {DW{1'b0}};

        if (INIT_FILE != "") 
        begin
            $readmemh(INIT_FILE, mem);
        end 
    end

    // Synchronous read & write (read-after-write same cycle gives new data)
    always @(posedge clk or negedge rst_b) 
    begin
        if (!rst_b)
            dout <= {DW{1'b0}};
        else if (write) begin
            mem[addr] <= din;
            dout <= {DW{1'b0}};        // read-after-write returneaza data scrisa
        end
        else if (read)
            dout <= mem[addr];
    end
endmodule

Memory/memory_512x16_init_tb.v
`timescale 1ns/1ps
`include "memory_512x16.v"

module memory_512x16_init_tb;
    reg clk;
    reg rst_b;
    reg write;
    reg read;
    reg [8:0] addr;
    reg [15:0] din;
    wire [15:0] dout;

    // Instanțierea modulului de memorie CU FISIER DE INITIALIZARE
    memory_512x16 #(
        .AW(9),
        .DW(16),
        .INIT_FILE("program.hex")  // incarca instructiuni din fisier
    ) mem (
        .clk(clk),
        .rst_b(rst_b),
        .write(write),
        .read(read),
        .addr(addr),
        .din(din),
        .dout(dout)
    );

    // Generare clock
    initial begin
        clk = 0;
        forever #50 clk = ~clk;  // perioada 100ns
    end

    // Test scenario
    initial begin
        $dumpfile("dump_init.vcd");
        $dumpvars(0, memory_512x16_init_tb);
        
        // Initializare
        rst_b = 0;
        write = 0;
        read = 0;
        addr = 9'd0;
        din = 16'd0;
        
        // Reset
        #100;
        rst_b = 1;
        #100;
        
        $display("=== Test memorie initializata din fisier ===");
        $display("Fisier: program.hex");
        $display("");
        
        // Citeste primele 16 adrese (incarcate din fisier)
        $display("--- Citire date incarcate din fisier ---");
        write = 0;
        read = 1;
        addr = 9'd0;
        
        repeat(16) begin
            #100;
            $display("Adresa %3d: 0x%h", addr, dout);
            addr = addr + 1;
        end
        
        // Verifica ca restul memoriei e 0
        $display("");
        $display("--- Verificare adrese neinitializate (ar trebui sa fie 0) ---");
        addr = 9'd16;
        #100;
        $display("Adresa %3d: 0x%h", addr, dout);
        
        addr = 9'd100;
        #100;
        $display("Adresa %3d: 0x%h", addr, dout);
        
        addr = 9'd511;
        #100;
        $display("Adresa %3d: 0x%h", addr, dout);
        
        // Test scriere peste date existente
        $display("");
        $display("--- Test suprascriere ---");
        write = 1;
        read = 0;
        addr = 9'd0;
        din = 16'hAAAA;
        #100;
        $display("Scris 0xAAAA la adresa 0");
        
        write = 0;
        read = 1;
        #100;
        $display("Citit de la adresa 0: 0x%h (asteptat: 0xAAAA)", dout);
        
        // Verifica adresa 1 (nu s-a schimbat)
        addr = 9'd1;
        #100;
        $display("Adresa 1 neschimbata: 0x%h (asteptat: 0x0002)", dout);
        
        #200;
        $display("");
        $display("=== Test finalizat! ===");
        $finish;
    end

    // Monitor pentru debug (optional - comenteaza daca e prea verbose)
    // initial begin
    //     $monitor("Time=%0t | read=%b addr=%d dout=0x%h", 
    //              $time, read, addr, dout);
    // end

endmodule

Memory/dump_init.vcd
$date
	Sat Nov 29 22:54:26 2025
$end
$version
	Icarus Verilog
$end
$timescale
	1ps
$end
$scope module memory_512x16_init_tb $end
$var wire 16 ! dout [15:0] $end
$var reg 9 " addr [8:0] $end
$var reg 1 # clk $end
$var reg 16 $ din [15:0] $end
$var reg 1 % read $end
$var reg 1 & rst_b $end
$var reg 1 ' write $end
$scope module mem $end
$var wire 9 ( addr [8:0] $end
$var wire 1 # clk $end
$var wire 16 ) din [15:0] $end
$var wire 1 % read $end
$var wire 1 & rst_b $end
$var wire 1 ' write $end
$var parameter 32 * AW $end
$var parameter 32 + DW $end
$var parameter 88 , INIT_FILE $end
$var reg 16 - dout [15:0] $end
$var integer 32 . i [31:0] $end
$upscope $end
$upscope $end
$enddefinitions $end
$comment Show the parameter values. $end
$dumpall
b111000001110010011011110110011101110010011000010110110100101110011010000110010101111000 ,
b10000 +
b1001 *
$end
#0
$dumpvars
b1000000000 .
b0 -
b0 )
b0 (
0'
0&
0%
b0 $
0#
b0 "
b0 !
$end
#50000
1#
#100000
0#
1&
#150000
1#
#200000
0#
1%
#250000
b1 !
b1 -
1#
#300000
0#
b1 "
b1 (
#350000
b10 !
b10 -
1#
#400000
0#
b10 "
b10 (
#450000
b11 !
b11 -
1#
#500000
0#
b11 "
b11 (
#550000
b1010101111001101 !
b1010101111001101 -
1#
#600000
0#
b100 "
b100 (
#650000
b1011111011101111 !
b1011111011101111 -
1#
#700000
0#
b101 "
b101 (
#750000
b1100101011111110 !
b1100101011111110 -
1#
#800000
0#
b110 "
b110 (
#850000
b1101111010101101 !
b1101111010101101 -
1#
#900000
0#
b111 "
b111 (
#950000
b1001000110100 !
b1001000110100 -
1#
#1000000
0#
b1000 "
b1000 (
#1050000
b101011001111000 !
b101011001111000 -
1#
#1100000
0#
b1001 "
b1001 (
#1150000
b1001101010111100 !
b1001101010111100 -
1#
#1200000
0#
b1010 "
b1010 (
#1250000
b1101111011110000 !
b1101111011110000 -
1#
#1300000
0#
b1011 "
b1011 (
#1350000
b1111111111111111 !
b1111111111111111 -
1#
#1400000
0#
b1100 "
b1100 (
#1450000
b0 !
b0 -
1#
#1500000
0#
b1101 "
b1101 (
#1550000
b1000100010001 !
b1000100010001 -
1#
#1600000
0#
b1110 "
b1110 (
#1650000
b10001000100010 !
b10001000100010 -
1#
#1700000
0#
b1111 "
b1111 (
#1750000
b11001100110011 !
b11001100110011 -
1#
#1800000
0#
b10000 "
b10000 (
#1850000
b0 !
b0 -
1#
#1900000
0#
b1100100 "
b1100100 (
#1950000
1#
#2000000
0#
b111111111 "
b111111111 (
#2050000
1#
#2100000
0#
b1010101010101010 $
b1010101010101010 )
b0 "
b0 (
0%
1'
#2150000
1#
#2200000
0#
1%
0'
#2250000
b1010101010101010 !
b1010101010101010 -
1#
#2300000
0#
b1 "
b1 (
#2350000
b10 !
b10 -
1#
