Memory/memory_512x16.v
module memory_512x16 #(
    parameter AW = 9,          // address width (512 = 2^9)
    parameter DW = 16,         // data width
    parameter INIT_FILE = ""   // optional: mem init (hex/binary)
)(
    input               clk,
    input               rst_b,
    input               write,      // write enable (active high)
    input               read,       // read enable  (active high)
    input  [AW-1:0]     addr,       // address
    input  [DW-1:0]     din,        // data in
    output reg [DW-1:0] dout        // data out
);

    reg [DW-1:0] mem [0:(1 << AW)-1];

    // Optional initialization
    integer i;
    initial begin
        for (i = 0; i < (1 << AW); i = i + 1)
                mem[i] = {DW{1'b0}};

        if (INIT_FILE != "") 
        begin
            $readmemh(INIT_FILE, mem);
        end 
    end

    // Synchronous read & write (read-after-write same cycle gives new data)
    always @(posedge clk or negedge rst_b) 
    begin
        if (!rst_b)
            dout <= {DW{1'b0}};
        else if (write) begin
            mem[addr] <= din;
            dout <= {DW{1'b0}};        // read-after-write returneaza data scrisa
        end
        else if (read)
            dout <= mem[addr];
    end
endmodule

Memory/memory_512x16_tb.v
`timescale 1ns/1ns
`include "memory_512x16.v"

module memory_512x16_tb;
    reg clk;
    reg rst_b;
    reg write;
    reg read;
    reg [8:0] addr;
    reg [15:0] din;
    wire [15:0] dout;

    // Instanțierea modulului de memorie
    memory_512x16 #(
        .AW(9),
        .DW(16),
        .INIT_FILE("")  // fără fișier de inițializare pentru test
    ) mem (
        .clk(clk),
        .rst_b(rst_b),
        .write(write),
        .read(read),
        .addr(addr),
        .din(din),
        .dout(dout)
    );

    // Generare clock
    initial begin
        clk = 0;
        forever #50 clk = ~clk;  // perioadă 100ns
    end

    // Test scenario
    initial begin
        $dumpfile("dump.vcd");
        $dumpvars(0, memory_512x16_tb, mem);
        
        // Inițializare
        rst_b = 0;
        write = 0;
        read = 0;
        addr = 9'd0;
        din = 16'd0;
        
        // Reset
        #100;
        rst_b = 1;
        #100;
        
        // Test 1: Scriere la adresa 0
        $display("Test 1: Scriere 0xABCD la adresa 0");
        write = 1;
        read = 0;
        addr = 9'd0;
        din = 16'hABCD;
        #100;
        
        // Test 2: Citire de la adresa 0
        $display("Test 2: Citire de la adresa 0");
        write = 0;
        read = 1;
        addr = 9'd0;
        #100;
        $display("Citit: 0x%h (asteptat: 0xABCD)", dout);
        
        // Test 3: Scriere secvențială la 10 adrese
        $display("Test 3: Scriere secventiala la 10 adrese");
        write = 1;
        read = 0;
        addr = 9'd0;
        repeat(10) begin
            din = {7'b0, addr};  // valoarea = adresa
            #100;
            addr = addr + 1;
        end
        
        // Test 4: Citire secvențială din 10 adrese
        $display("Test 4: Citire secventiala din 10 adrese");
        write = 0;
        read = 1;
        addr = 9'd0;
        repeat(10) begin
            #100;
            $display("Adresa %d: citit 0x%h", addr, dout);
            addr = addr + 1;
        end
        
        // Test 5: Scriere la adresa maximă (511)
        $display("Test 5: Scriere 0x1234 la adresa 511");
        write = 1;
        read = 0;
        addr = 9'd511;
        din = 16'h1234;
        #100;
        
        // Test 6: Citire de la adresa maximă
        $display("Test 6: Citire de la adresa 511");
        write = 0;
        read = 1;
        #100;
        $display("Citit: 0x%h (asteptat: 0x1234)", dout);
        
        // Test 7: Fără write (nu scrie)
        $display("Test 7: Incercare scriere cu write=0");
        write = 0;
        read = 0;
        addr = 9'd100;
        din = 16'hFFFF;
        #100;
        read = 1;
        #100;
        $display("Citit: 0x%h (nu ar trebui sa fie 0xFFFF)", dout);
        
        // Test 8: Reset în timpul operării
        $display("Test 8: Reset in timpul operarii");
        write = 1;
        read = 0;
        addr = 9'd50;
        din = 16'hDEAD;
        #50;
        rst_b = 0;
        #100;
        rst_b = 1;
        write = 0;
        read = 1;
        #100;
        $display("Citit dupa reset: 0x%h", dout);
        
        // Test 9: Read-after-write în același ciclu
        $display("Test 9: Read-after-write test");
        write = 1;
        read = 0;
        addr = 9'd200;
        din = 16'hCAFE;
        #100;
        $display("Read-after-write: dout=0x%h (asteptat: 0xCAFE)", dout);
        write = 0;
        
        #200;
        $display("=== Test finalizat! ===");
        $finish;
    end

    // Monitor pentru debug
    initial begin
        $monitor("Time=%0t | rst_b=%b write=%b read=%b addr=%d din=0x%h dout=0x%h", 
                 $time, rst_b, write, read, addr, din, dout);
    end

endmodule

Memory/dump.vcd
$date
	Mon Dec 29 14:46:38 2025
$end
$version
	Icarus Verilog
$end
$timescale
	1ns
$end
$scope module memory_512x16_tb $end
$var wire 16 ! dout [15:0] $end
$var reg 9 " addr [8:0] $end
$var reg 1 # clk $end
$var reg 16 $ din [15:0] $end
$var reg 1 % read $end
$var reg 1 & rst_b $end
$var reg 1 ' write $end
$scope module mem $end
$var wire 9 ( addr [8:0] $end
$var wire 1 # clk $end
$var wire 16 ) din [15:0] $end
$var wire 1 % read $end
$var wire 1 & rst_b $end
$var wire 1 ' write $end
$var parameter 32 * AW $end
$var parameter 32 + DW $end
$var parameter 0 , INIT_FILE $end
$var reg 16 - dout [15:0] $end
$var integer 32 . i [31:0] $end
$upscope $end
$upscope $end
$scope module memory_512x16_tb $end
$scope module mem $end
$upscope $end
$upscope $end
$enddefinitions $end
$comment Show the parameter values. $end
$dumpall
b ,
b10000 +
b1001 *
$end
#0
$dumpvars
b1000000000 .
b0 -
b0 )
b0 (
0'
0&
0%
b0 $
0#
b0 "
b0 !
$end
#50
1#
#100
0#
1&
#150
1#
#200
0#
b1010101111001101 $
b1010101111001101 )
1'
#250
1#
#300
0#
1%
0'
#350
b1010101111001101 !
b1010101111001101 -
1#
#400
0#
b0 $
b0 )
0%
1'
#450
b0 !
b0 -
1#
#500
0#
b1 $
b1 )
b1 "
b1 (
#550
1#
#600
0#
b10 $
b10 )
b10 "
b10 (
#650
1#
#700
0#
b11 $
b11 )
b11 "
b11 (
#750
1#
#800
0#
b100 $
b100 )
b100 "
b100 (
#850
1#
#900
0#
b101 $
b101 )
b101 "
b101 (
#950
1#
#1000
0#
b110 $
b110 )
b110 "
b110 (
#1050
1#
#1100
0#
b111 $
b111 )
b111 "
b111 (
#1150
1#
#1200
0#
b1000 $
b1000 )
b1000 "
b1000 (
#1250
1#
#1300
0#
b1001 $
b1001 )
b1001 "
b1001 (
#1350
1#
#1400
0#
1%
0'
b0 "
b0 (
#1450
1#
#1500
0#
b1 "
b1 (
#1550
b1 !
b1 -
1#
#1600
0#
b10 "
b10 (
#1650
b10 !
b10 -
1#
#1700
0#
b11 "
b11 (
#1750
b11 !
b11 -
1#
#1800
0#
b100 "
b100 (
#1850
b100 !
b100 -
1#
#1900
0#
b101 "
b101 (
#1950
b101 !
b101 -
1#
#2000
0#
b110 "
b110 (
#2050
b110 !
b110 -
1#
#2100
0#
b111 "
b111 (
#2150
b111 !
b111 -
1#
#2200
0#
b1000 "
b1000 (
#2250
b1000 !
b1000 -
1#
#2300
0#
b1001 "
b1001 (
#2350
b1001 !
b1001 -
1#
#2400
0#
b1001000110100 $
b1001000110100 )
0%
1'
b111111111 "
b111111111 (
#2450
b0 !
b0 -
1#
#2500
0#
1%
0'
#2550
b1001000110100 !
b1001000110100 -
1#
#2600
0#
b1111111111111111 $
b1111111111111111 )
b1100100 "
b1100100 (
0%
#2650
1#
#2700
0#
1%
#2750
b0 !
b0 -
1#
#2800
0#
b1101111010101101 $
b1101111010101101 )
b110010 "
b110010 (
0%
1'
#2850
1#
0&
#2900
0#
#2950
1#
1%
0'
1&
#3000
0#
#3050
1#
b1100101011111110 $
b1100101011111110 )
b11001000 "
b11001000 (
0%
1'
#3100
0#
#3150
1#
0'
