Processor/ALU16/Registers/ffd.v
module ffd (
    input clk,rst_b,
    input en,d,
    output reg q
);
    always@(posedge clk or negedge rst_b)
    begin
        if(!rst_b)
            q<=1'b0;
        else if(en)
            q<=d;
    end
endmodule

ALU-8-Bits/Registers/counter.v
module counter (
    input clk, rst_b, c_up,
    output [3:0] out
);

    ffd f0(
        .clk(clk),
        .rst_b(rst_b),
        .en(c_up),
        .d(~out[0]),
        .q(out[0])
    );
    ffd f1(
        .clk(clk),
        .rst_b(rst_b),
        .en(c_up),
        .d(out[0] ^ out[1]),
        .q(out[1])
    );
    ffd f2(
        .clk(clk),
        .rst_b(rst_b),
        .en(c_up),
        .d((out[2] & (~out[1])) | (out[2] & (~out[0])) | ((~out[2]) & out[1] & out[0])),
        .q(out[2])
    );
    ffd f3(
        .clk(clk),
        .rst_b(rst_b),
        .en(c_up),
        .d((~out[1] & out[3]) | (out[3] & ~out[2]) | (~out[0] & out[3]) | (out[1] & out[0] & ~out[3] & out[2])),
        .q(out[3])
    );
endmodule

ALU-8-Bits/Registers/counter_tb.v
module counter_tb;

    reg clk, rst_b, c_up;
    wire [3:0] out;

    counter c1 (
      .clk(clk),
      .rst_b(rst_b),
      .c_up(c_up),
      .out(out)
    );

    initial begin
      $dumpfile("dump.vcd");
      $dumpvars;
      clk = 0;
      rst_b = 1;
      c_up = 1;
      #10; rst_b = 0;
      #20; rst_b = 1;
    end

    integer i;
    initial begin
        for(i=0;i<100;i=i+1)
        begin
            #50; clk=~clk;
        end
        #50;
    end

    initial begin
        $display("Time\tout");
        $monitor("%0t\t%b", $time, out);
    end
endmodule

ALU-8-Bits/Registers/dump.vcd
$date
	Thu Oct 23 23:48:00 2025
$end
$version
	Icarus Verilog
$end
$timescale
	1s
$end
$scope module counter_tb $end
$var wire 4 ! out [3:0] $end
$var reg 1 " c_up $end
$var reg 1 # clk $end
$var reg 1 $ rst_b $end
$var integer 32 % i [31:0] $end
$scope module c1 $end
$var wire 1 " c_up $end
$var wire 1 # clk $end
$var wire 1 $ rst_b $end
$var wire 4 & out [3:0] $end
$scope module f0 $end
$var wire 1 # clk $end
$var wire 1 ' d $end
$var wire 1 " en $end
$var wire 1 $ rst_b $end
$var reg 1 ( q $end
$upscope $end
$scope module f1 $end
$var wire 1 # clk $end
$var wire 1 ) d $end
$var wire 1 " en $end
$var wire 1 $ rst_b $end
$var reg 1 * q $end
$upscope $end
$scope module f2 $end
$var wire 1 # clk $end
$var wire 1 + d $end
$var wire 1 " en $end
$var wire 1 $ rst_b $end
$var reg 1 , q $end
$upscope $end
$scope module f3 $end
$var wire 1 # clk $end
$var wire 1 - d $end
$var wire 1 " en $end
$var wire 1 $ rst_b $end
$var reg 1 . q $end
$upscope $end
$upscope $end
$upscope $end
$enddefinitions $end
$comment Show the parameter values. $end
$dumpall
$end
#0
$dumpvars
x.
x-
x,
x+
x*
x)
x(
x'
bx &
b0 %
1$
0#
1"
bx !
$end
#10
0+
0-
1'
0)
0(
0*
0,
b0 !
b0 &
0.
0$
#30
1$
#50
1)
0'
b1 !
b1 &
1(
b1 %
1#
#100
b10 %
0#
#150
1'
0(
b10 !
b10 &
1*
b11 %
1#
#200
b100 %
0#
#250
1+
0)
0'
b11 !
b11 &
1(
b101 %
1#
#300
b110 %
0#
#350
1+
0-
1'
0(
0*
b100 !
b100 &
1,
b111 %
1#
#400
b1000 %
0#
#450
1)
0'
b101 !
b101 &
1(
b1001 %
1#
#500
b1010 %
0#
#550
1'
0(
b110 !
b110 &
1*
b1011 %
1#
#600
b1100 %
0#
#650
1-
0+
0)
0'
b111 !
b111 &
1(
b1101 %
1#
#700
b1110 %
0#
#750
1-
1'
0(
0*
0,
b1000 !
b1000 &
1.
b1111 %
1#
#800
b10000 %
0#
#850
1)
0'
b1001 !
b1001 &
1(
b10001 %
1#
#900
b10010 %
0#
#950
1'
0(
b1010 !
b1010 &
1*
b10011 %
1#
#1000
b10100 %
0#
#1050
1+
0)
0'
b1011 !
b1011 &
1(
b10101 %
1#
#1100
b10110 %
0#
#1150
1+
1'
0(
0*
b1100 !
b1100 &
1,
b10111 %
1#
#1200
b11000 %
0#
#1250
1)
0'
b1101 !
b1101 &
1(
b11001 %
1#
#1300
b11010 %
0#
#1350
1'
0(
b1110 !
b1110 &
1*
b11011 %
1#
#1400
b11100 %
0#
#1450
0-
0+
0)
0'
b1111 !
b1111 &
1(
b11101 %
1#
#1500
b11110 %
0#
#1550
1'
0(
0*
0,
b0 !
b0 &
0.
b11111 %
1#
#1600
b100000 %
0#
#1650
1)
0'
b1 !
b1 &
1(
b100001 %
1#
#1700
b100010 %
0#
#1750
1'
0(
b10 !
b10 &
1*
b100011 %
1#
#1800
b100100 %
0#
#1850
1+
0)
0'
b11 !
b11 &
1(
b100101 %
1#
#1900
b100110 %
0#
#1950
1+
0-
1'
0(
0*
b100 !
b100 &
1,
b100111 %
1#
#2000
b101000 %
0#
#2050
1)
0'
b101 !
b101 &
1(
b101001 %
1#
#2100
b101010 %
0#
#2150
1'
0(
b110 !
b110 &
1*
b101011 %
1#
#2200
b101100 %
0#
#2250
1-
0+
0)
0'
b111 !
b111 &
1(
b101101 %
1#
#2300
b101110 %
0#
#2350
1-
1'
0(
0*
0,
b1000 !
b1000 &
1.
b101111 %
1#
#2400
b110000 %
0#
#2450
1)
0'
b1001 !
b1001 &
1(
b110001 %
1#
#2500
b110010 %
0#
#2550
1'
0(
b1010 !
b1010 &
1*
b110011 %
1#
#2600
b110100 %
0#
#2650
1+
0)
0'
b1011 !
b1011 &
1(
b110101 %
1#
#2700
b110110 %
0#
#2750
1+
1'
0(
0*
b1100 !
b1100 &
1,
b110111 %
1#
#2800
b111000 %
0#
#2850
1)
0'
b1101 !
b1101 &
1(
b111001 %
1#
#2900
b111010 %
0#
#2950
1'
0(
b1110 !
b1110 &
1*
b111011 %
1#
#3000
b111100 %
0#
#3050
0-
0+
0)
0'
b1111 !
b1111 &
1(
b111101 %
1#
#3100
b111110 %
0#
#3150
1'
0(
0*
0,
b0 !
b0 &
0.
b111111 %
1#
#3200
b1000000 %
0#
#3250
1)
0'
b1 !
b1 &
1(
b1000001 %
1#
#3300
b1000010 %
0#
#3350
1'
0(
b10 !
b10 &
1*
b1000011 %
1#
#3400
b1000100 %
0#
#3450
1+
0)
0'
b11 !
b11 &
1(
b1000101 %
1#
#3500
b1000110 %
0#
#3550
1+
0-
1'
0(
0*
b100 !
b100 &
1,
b1000111 %
1#
#3600
b1001000 %
0#
#3650
1)
0'
b101 !
b101 &
1(
b1001001 %
1#
#3700
b1001010 %
0#
#3750
1'
0(
b110 !
b110 &
1*
b1001011 %
1#
#3800
b1001100 %
0#
#3850
1-
0+
0)
0'
b111 !
b111 &
1(
b1001101 %
1#
#3900
b1001110 %
0#
#3950
1-
1'
0(
0*
0,
b1000 !
b1000 &
1.
b1001111 %
1#
#4000
b1010000 %
0#
#4050
1)
0'
b1001 !
b1001 &
1(
b1010001 %
1#
#4100
b1010010 %
0#
#4150
1'
0(
b1010 !
b1010 &
1*
b1010011 %
1#
#4200
b1010100 %
0#
#4250
1+
0)
0'
b1011 !
b1011 &
1(
b1010101 %
1#
#4300
b1010110 %
0#
#4350
1+
1'
0(
0*
b1100 !
b1100 &
1,
b1010111 %
1#
#4400
b1011000 %
0#
#4450
1)
0'
b1101 !
b1101 &
1(
b1011001 %
1#
#4500
b1011010 %
0#
#4550
1'
0(
b1110 !
b1110 &
1*
b1011011 %
1#
#4600
b1011100 %
0#
#4650
0-
0+
0)
0'
b1111 !
b1111 &
1(
b1011101 %
1#
#4700
b1011110 %
0#
#4750
1'
0(
0*
0,
b0 !
b0 &
0.
b1011111 %
1#
#4800
b1100000 %
0#
#4850
1)
0'
b1 !
b1 &
1(
b1100001 %
1#
#4900
b1100010 %
0#
#4950
1'
0(
b10 !
b10 &
1*
b1100011 %
1#
#5000
b1100100 %
0#
