ALU16/Combinational/comparator/comp4.v
module comparator_1bit
(
    input A,
    input B,
    input A_greater_in,
    input A_equal_in,
    input A_less_in,
    output A_greater_out,
    output A_equal_out,
    output A_less_out
);

assign A_greater_out = (A_greater_in) | (A_equal_in &  A & ~B);
assign A_less_out    = (A_less_in)    | (A_equal_in & ~A &  B);
assign A_equal_out   = (A_equal_in & ~(A ^ B));

endmodule

module comp4
(
    input [3:0] a,
    input [3:0] b,
    output lt,
    output eq,
    output gt
);

wire [3:0] greater;
wire [3:0] equal;
wire [3:0] less;

comparator_1bit comp3(a[3], b[3], 1'b0, 1'b1, 1'b0, greater[3], equal[3], less[3]);
comparator_1bit comp2(a[2], b[2], greater[3], equal[3], less[3], greater[2], equal[2], less[2]);
comparator_1bit comp1(a[1], b[1], greater[2], equal[2], less[2], greater[1], equal[1], less[1]);
comparator_1bit comp0(a[0], b[0], greater[1], equal[1], less[1], gt, eq, lt);

endmodule

ALU16/Combinational/comparator/comp4_tb.v
`include "./comp4.v"
module comp4_tb;

reg [3:0] a, b;
wire eq, gt, lt;

comp4 comp(
	.a(a),
	.b(b),
	.eq(eq),
	.gt(gt),
	.lt(lt)
);

initial begin
	$dumpfile("dump.vcd");
	$dumpvars;
end

integer i, j;
initial begin
  for(i = 0; i < 16; i = i + 1) 
  begin
		a = i;
		for(j = 0; j < 16; j = j + 1) 
		begin
			b = j;
			#10;
			$display("a-%b b-%b %b%b%b", a, b, lt, eq, gt);
		end
		#10;
  end
end


endmodule

Processor/ALU16/Combinational/comparator/dump.vcd
$date
	Sat Nov  8 18:49:33 2025
$end
$version
	Icarus Verilog
$end
$timescale
	1s
$end
$scope module comp4_tb $end
$var wire 1 ! lt $end
$var wire 1 " gt $end
$var wire 1 # eq $end
$var reg 4 $ a [3:0] $end
$var reg 4 % b [3:0] $end
$var integer 32 & i [31:0] $end
$var integer 32 ' j [31:0] $end
$scope module comp $end
$var wire 4 ( a [3:0] $end
$var wire 4 ) b [3:0] $end
$var wire 1 ! lt $end
$var wire 4 * less [3:0] $end
$var wire 1 " gt $end
$var wire 4 + greater [3:0] $end
$var wire 4 , equal [3:0] $end
$var wire 1 # eq $end
$scope module comp0 $end
$var wire 1 - A $end
$var wire 1 . A_equal_in $end
$var wire 1 # A_equal_out $end
$var wire 1 / A_greater_in $end
$var wire 1 " A_greater_out $end
$var wire 1 0 A_less_in $end
$var wire 1 ! A_less_out $end
$var wire 1 1 B $end
$upscope $end
$scope module comp1 $end
$var wire 1 2 A $end
$var wire 1 3 A_equal_in $end
$var wire 1 4 A_equal_out $end
$var wire 1 5 A_greater_in $end
$var wire 1 6 A_greater_out $end
$var wire 1 7 A_less_in $end
$var wire 1 8 A_less_out $end
$var wire 1 9 B $end
$upscope $end
$scope module comp2 $end
$var wire 1 : A $end
$var wire 1 ; A_equal_in $end
$var wire 1 < A_equal_out $end
$var wire 1 = A_greater_in $end
$var wire 1 > A_greater_out $end
$var wire 1 ? A_less_in $end
$var wire 1 @ A_less_out $end
$var wire 1 A B $end
$upscope $end
$scope module comp3 $end
$var wire 1 B A $end
$var wire 1 C A_equal_in $end
$var wire 1 D A_equal_out $end
$var wire 1 E A_greater_in $end
$var wire 1 F A_greater_out $end
$var wire 1 G A_less_in $end
$var wire 1 H A_less_out $end
$var wire 1 I B $end
$upscope $end
$upscope $end
$upscope $end
$enddefinitions $end
$comment Show the parameter values. $end
$dumpall
$end
#0
$dumpvars
0I
0H
0G
0F
0E
1D
1C
0B
0A
0@
0?
0>
0=
1<
1;
0:
09
08
07
06
05
14
13
02
01
00
0/
1.
0-
b111z ,
b0z +
b0z *
b0 )
b0 (
b0 '
b0 &
b0 %
b0 $
1#
0"
0!
$end
#10
0#
1!
11
b1 %
b1 )
b1 '
#20
0.
10
b110z ,
04
0#
b1z *
18
1!
19
01
b10 %
b10 )
b10 '
#30
11
b11 %
b11 )
b11 '
#40
0#
03
1!
0.
17
0<
10
b100z ,
04
1@
b11z *
18
1A
09
01
b100 %
b100 )
b100 '
#50
11
b101 %
b101 )
b101 '
#60
19
01
b110 %
b110 )
b110 '
#70
11
b111 %
b111 )
b111 '
#80
0#
1!
0.
10
04
0;
18
03
1?
0D
17
b0z ,
0<
1H
b111z *
1@
1I
0A
09
01
b1000 %
b1000 )
b1000 '
#90
11
b1001 %
b1001 )
b1001 '
#100
19
01
b1010 %
b1010 )
b1010 '
#110
11
b1011 %
b1011 )
b1011 '
#120
1A
09
01
b1100 %
b1100 )
b1100 '
#130
11
b1101 %
b1101 )
b1101 '
#140
19
01
b1110 %
b1110 )
b1110 '
#150
11
b1111 %
b1111 )
b1111 '
#160
b10000 '
#170
1"
0!
1.
00
14
08
13
07
1<
0@
1;
0?
b111z ,
1D
b0z *
0H
0I
0A
09
01
1-
b0 %
b0 )
b0 '
b1 $
b1 (
b1 &
#180
0"
1#
11
b1 %
b1 )
b1 '
#190
1!
0.
10
b110z ,
04
0"
0#
b1z *
18
19
01
b10 %
b10 )
b10 '
#200
11
b11 %
b11 )
b11 '
#210
0"
03
1!
0.
17
0<
10
b100z ,
04
1@
b11z *
18
1A
09
01
b100 %
b100 )
b100 '
#220
11
b101 %
b101 )
b101 '
#230
19
01
b110 %
b110 )
b110 '
#240
11
b111 %
b111 )
b111 '
#250
0"
1!
0.
10
04
0;
18
03
1?
0D
17
b0z ,
0<
1H
b111z *
1@
1I
0A
09
01
b1000 %
b1000 )
b1000 '
#260
11
b1001 %
b1001 )
b1001 '
#270
19
01
b1010 %
b1010 )
b1010 '
#280
11
b1011 %
b1011 )
b1011 '
#290
1A
09
01
b1100 %
b1100 )
b1100 '
#300
11
b1101 %
b1101 )
b1101 '
#310
19
01
b1110 %
b1110 )
b1110 '
#320
11
b1111 %
b1111 )
b1111 '
#330
b10000 '
#340
1"
1/
b1z +
16
0!
00
08
13
07
1<
0@
1;
0?
b110z ,
1D
b0z *
0H
0I
0A
09
01
12
0-
b0 %
b0 )
b0 '
b10 $
b10 (
b10 &
#350
11
b1 %
b1 )
b1 '
#360
0"
1#
0/
1.
b0z +
06
b111z ,
14
19
01
b10 %
b10 )
b10 '
#370
0#
1!
11
b11 %
b11 )
b11 '
#380
10
0"
18
03
0/
0.
17
0<
b0z +
06
b100z ,
04
0#
b11z *
1@
1!
1A
09
01
b100 %
b100 )
b100 '
#390
11
b101 %
b101 )
b101 '
#400
19
01
b110 %
b110 )
b110 '
#410
11
b111 %
b111 )
b111 '
#420
0"
0/
b0z +
06
1!
10
0;
18
03
1?
0D
17
b0z ,
0<
1H
b111z *
1@
1I
0A
09
01
b1000 %
b1000 )
b1000 '
#430
11
b1001 %
b1001 )
b1001 '
#440
19
01
b1010 %
b1010 )
b1010 '
#450
11
b1011 %
b1011 )
b1011 '
#460
1A
09
01
b1100 %
b1100 )
b1100 '
#470
11
b1101 %
b1101 )
b1101 '
#480
19
01
b1110 %
b1110 )
b1110 '
#490
11
b1111 %
b1111 )
b1111 '
#500
b10000 '
#510
1"
1/
b1z +
16
0!
00
08
13
07
1<
0@
1;
0?
b110z ,
1D
b0z *
0H
0I
0A
09
01
1-
b0 %
b0 )
b0 '
b11 $
b11 (
b11 &
#520
11
b1 %
b1 )
b1 '
#530
1"
0/
1.
b0z +
06
b111z ,
14
19
01
b10 %
b10 )
b10 '
#540
0"
1#
11
b11 %
b11 )
b11 '
#550
1!
10
18
03
0/
0.
17
0<
b0z +
06
b100z ,
04
0"
0#
b11z *
1@
1A
09
01
b100 %
b100 )
b100 '
#560
11
b101 %
b101 )
b101 '
#570
19
01
b110 %
b110 )
b110 '
#580
11
b111 %
b111 )
b111 '
#590
0"
0/
b0z +
06
1!
10
0;
18
03
1?
0D
17
b0z ,
0<
1H
b111z *
1@
1I
0A
09
01
b1000 %
b1000 )
b1000 '
#600
11
b1001 %
b1001 )
b1001 '
#610
19
01
b1010 %
b1010 )
b1010 '
#620
11
b1011 %
b1011 )
b1011 '
#630
1A
09
01
b1100 %
b1100 )
b1100 '
#640
11
b1101 %
b1101 )
b1101 '
#650
19
01
b1110 %
b1110 )
b1110 '
#660
11
b1111 %
b1111 )
b1111 '
#670
b10000 '
#680
1"
1/
16
0!
15
00
b11z +
1>
08
07
0@
1;
0?
b100z ,
1D
b0z *
0H
0I
0A
09
01
1:
02
0-
b0 %
b0 )
b0 '
b100 $
b100 (
b100 &
#690
11
b1 %
b1 )
b1 '
#700
19
01
b10 %
b10 )
b10 '
#710
11
b11 %
b11 )
b11 '
#720
0"
1#
0/
1.
06
14
05
13
b0z +
0>
b111z ,
1<
1A
09
01
b100 %
b100 )
b100 '
#730
0#
1!
11
b101 %
b101 )
b101 '
#740
0.
10
b110z ,
04
0#
b1z *
18
1!
19
01
b110 %
b110 )
b110 '
#750
11
b111 %
b111 )
b111 '
#760
0"
0/
17
06
0#
1@
0;
05
03
1!
0.
1?
0D
b0z +
0>
0<
10
b0z ,
04
1H
b111z *
18
1I
0A
09
01
b1000 %
b1000 )
b1000 '
#770
11
b1001 %
b1001 )
b1001 '
#780
19
01
b1010 %
b1010 )
b1010 '
#790
11
b1011 %
b1011 )
b1011 '
#800
1A
09
01
b1100 %
b1100 )
b1100 '
#810
11
b1101 %
b1101 )
b1101 '
#820
19
01
b1110 %
b1110 )
b1110 '
#830
11
b1111 %
b1111 )
b1111 '
#840
b10000 '
#850
1"
1/
16
0!
15
00
b11z +
1>
08
07
0@
1;
0?
b100z ,
1D
b0z *
0H
0I
0A
09
01
1-
b0 %
b0 )
b0 '
b101 $
b101 (
b101 &
#860
11
b1 %
b1 )
b1 '
#870
19
01
b10 %
b10 )
b10 '
#880
11
b11 %
b11 )
b11 '
#890
1"
0/
1.
06
14
05
13
b0z +
0>
b111z ,
1<
1A
09
01
b100 %
b100 )
b100 '
#900
0"
1#
11
b101 %
b101 )
b101 '
#910
1!
0.
10
b110z ,
04
0"
0#
b1z *
18
19
01
b110 %
b110 )
b110 '
#920
11
b111 %
b111 )
b111 '
#930
0"
0/
17
06
1@
0;
05
03
1!
0.
1?
0D
b0z +
0>
0<
10
b0z ,
04
1H
b111z *
18
1I
0A
09
01
b1000 %
b1000 )
b1000 '
#940
11
b1001 %
b1001 )
b1001 '
#950
19
01
b1010 %
b1010 )
b1010 '
#960
11
b1011 %
b1011 )
b1011 '
#970
1A
09
01
b1100 %
b1100 )
b1100 '
#980
11
b1101 %
b1101 )
b1101 '
#990
19
01
b1110 %
b1110 )
b1110 '
#1000
11
b1111 %
b1111 )
b1111 '
#1010
b10000 '
#1020
1"
1/
16
0!
15
00
b11z +
1>
08
07
0@
1;
0?
b100z ,
1D
b0z *
0H
0I
0A
09
01
12
0-
b0 %
b0 )
b0 '
b110 $
b110 (
b110 &
#1030
11
b1 %
b1 )
b1 '
#1040
19
01
b10 %
b10 )
b10 '
#1050
11
b11 %
b11 )
b11 '
#1060
1"
1/
16
05
13
b1z +
0>
b110z ,
1<
1A
09
01
b100 %
b100 )
b100 '
#1070
11
b101 %
b101 )
b101 '
#1080
0"
1#
0/
1.
b0z +
06
b111z ,
14
19
01
b110 %
b110 )
b110 '
#1090
0#
1!
11
b111 %
b111 )
b111 '
#1100
10
18
17
0"
1@
0;
05
03
0/
0.
1?
0D
0>
0<
b0z +
06
b0z ,
04
0#
b111z *
1H
1!
1I
0A
09
01
b1000 %
b1000 )
b1000 '
#1110
11
b1001 %
b1001 )
b1001 '
#1120
19
01
b1010 %
b1010 )
b1010 '
#1130
11
b1011 %
b1011 )
b1011 '
#1140
1A
09
01
b1100 %
b1100 )
b1100 '
#1150
11
b1101 %
b1101 )
b1101 '
#1160
19
01
b1110 %
b1110 )
b1110 '
#1170
11
b1111 %
b1111 )
b1111 '
#1180
b10000 '
#1190
1"
1/
16
0!
15
00
b11z +
1>
08
07
0@
1;
0?
b100z ,
1D
b0z *
0H
0I
0A
09
01
1-
b0 %
b0 )
b0 '
b111 $
b111 (
b111 &
#1200
11
b1 %
b1 )
b1 '
#1210
19
01
b10 %
b10 )
b10 '
#1220
11
b11 %
b11 )
b11 '
#1230
1"
1/
16
05
13
b1z +
0>
b110z ,
1<
1A
09
01
b100 %
b100 )
b100 '
#1240
11
b101 %
b101 )
b101 '
#1250
1"
0/
1.
b0z +
06
b111z ,
14
19
01
b110 %
b110 )
b110 '
#1260
0"
1#
11
b111 %
b111 )
b111 '
#1270
1!
10
18
17
1@
0;
05
03
0/
0.
1?
0D
0>
0<
b0z +
06
b0z ,
04
0"
0#
b111z *
1H
1I
0A
09
01
b1000 %
b1000 )
b1000 '
#1280
11
b1001 %
b1001 )
b1001 '
#1290
19
01
b1010 %
b1010 )
b1010 '
#1300
11
b1011 %
b1011 )
b1011 '
#1310
1A
09
01
b1100 %
b1100 )
b1100 '
#1320
11
b1101 %
b1101 )
b1101 '
#1330
19
01
b1110 %
b1110 )
b1110 '
#1340
11
b1111 %
b1111 )
b1111 '
#1350
b10000 '
#1360
1"
0!
1/
00
16
08
15
07
1>
0@
1=
0?
b111z +
1F
b0z *
0H
0I
0A
09
01
1B
0:
02
0-
b0 %
b0 )
b0 '
b1000 $
b1000 (
b1000 &
#1370
11
b1 %
b1 )
b1 '
#1380
19
01
b10 %
b10 )
b10 '
#1390
11
b11 %
b11 )
b11 '
#1400
1A
09
01
b100 %
b100 )
b100 '
#1410
11
b101 %
b101 )
b101 '
#1420
19
01
b110 %
b110 )
b110 '
#1430
11
b111 %
b111 )
b111 '
#1440
0"
1#
0/
1.
06
14
05
13
0>
1<
0=
1;
b0z +
0F
b111z ,
1D
1I
0A
09
01
b1000 %
b1000 )
b1000 '
#1450
0#
1!
11
b1001 %
b1001 )
b1001 '
#1460
0.
10
b110z ,
04
0#
b1z *
18
1!
19
01
b1010 %
b1010 )
b1010 '
#1470
11
b1011 %
b1011 )
b1011 '
#1480
0#
03
1!
0.
17
0<
10
b100z ,
04
1@
b11z *
18
1A
09
01
b1100 %
b1100 )
b1100 '
#1490
11
b1101 %
b1101 )
b1101 '
#1500
19
01
b1110 %
b1110 )
b1110 '
#1510
11
b1111 %
b1111 )
b1111 '
#1520
b10000 '
#1530
1"
1/
16
15
0!
0.
1>
00
04
1=
0;
08
03
b111z +
1F
0D
07
b0z ,
0<
b0z *
0@
0I
0A
09
01
1-
b0 %
b0 )
b0 '
b1001 $
b1001 (
b1001 &
#1540
11
b1 %
b1 )
b1 '
#1550
19
01
b10 %
b10 )
b10 '
#1560
11
b11 %
b11 )
b11 '
#1570
1A
09
01
b100 %
b100 )
b100 '
#1580
11
b101 %
b101 )
b101 '
#1590
19
01
b110 %
b110 )
b110 '
#1600
11
b111 %
b111 )
b111 '
#1610
1"
0/
1.
06
14
05
13
0>
1<
0=
1;
b0z +
0F
b111z ,
1D
1I
0A
09
01
b1000 %
b1000 )
b1000 '
#1620
0"
1#
11
b1001 %
b1001 )
b1001 '
#1630
1!
0.
10
b110z ,
04
0"
0#
b1z *
18
19
01
b1010 %
b1010 )
b1010 '
#1640
11
b1011 %
b1011 )
b1011 '
#1650
0"
03
1!
0.
17
0<
10
b100z ,
04
1@
b11z *
18
1A
09
01
b1100 %
b1100 )
b1100 '
#1660
11
b1101 %
b1101 )
b1101 '
#1670
19
01
b1110 %
b1110 )
b1110 '
#1680
11
b1111 %
b1111 )
b1111 '
#1690
b10000 '
#1700
1"
1/
16
15
0!
1>
00
1=
0;
08
03
b111z +
1F
0D
07
b0z ,
0<
b0z *
0@
0I
0A
09
01
12
0-
b0 %
b0 )
b0 '
b1010 $
b1010 (
b1010 &
#1710
11
b1 %
b1 )
b1 '
#1720
19
01
b10 %
b10 )
b10 '
#1730
11
b11 %
b11 )
b11 '
#1740
1A
09
01
b100 %
b100 )
b100 '
#1750
11
b101 %
b101 )
b101 '
#1760
19
01
b110 %
b110 )
b110 '
#1770
11
b111 %
b111 )
b111 '
#1780
1"
1/
16
05
13
0>
1<
0=
1;
b1z +
0F
b110z ,
1D
1I
0A
09
01
b1000 %
b1000 )
b1000 '
#1790
11
b1001 %
b1001 )
b1001 '
#1800
0"
1#
0/
1.
b0z +
06
b111z ,
14
19
01
b1010 %
b1010 )
b1010 '
#1810
0#
1!
11
b1011 %
b1011 )
b1011 '
#1820
10
0"
18
03
0/
0.
17
0<
b0z +
06
b100z ,
04
0#
b11z *
1@
1!
1A
09
01
b1100 %
b1100 )
b1100 '
#1830
11
b1101 %
b1101 )
b1101 '
#1840
19
01
b1110 %
b1110 )
b1110 '
#1850
11
b1111 %
b1111 )
b1111 '
#1860
b10000 '
#1870
1"
1/
16
15
0!
1>
00
1=
0;
08
03
b111z +
1F
0D
07
b0z ,
0<
b0z *
0@
0I
0A
09
01
1-
b0 %
b0 )
b0 '
b1011 $
b1011 (
b1011 &
#1880
11
b1 %
b1 )
b1 '
#1890
19
01
b10 %
b10 )
b10 '
#1900
11
b11 %
b11 )
b11 '
#1910
1A
09
01
b100 %
b100 )
b100 '
#1920
11
b101 %
b101 )
b101 '
#1930
19
01
b110 %
b110 )
b110 '
#1940
11
b111 %
b111 )
b111 '
#1950
1"
1/
16
05
13
0>
1<
0=
1;
b1z +
0F
b110z ,
1D
1I
0A
09
01
b1000 %
b1000 )
b1000 '
#1960
11
b1001 %
b1001 )
b1001 '
#1970
1"
0/
1.
b0z +
06
b111z ,
14
19
01
b1010 %
b1010 )
b1010 '
#1980
0"
1#
11
b1011 %
b1011 )
b1011 '
#1990
1!
10
18
03
0/
0.
17
0<
b0z +
06
b100z ,
04
0"
0#
b11z *
1@
1A
09
01
b1100 %
b1100 )
b1100 '
#2000
11
b1101 %
b1101 )
b1101 '
#2010
19
01
b1110 %
b1110 )
b1110 '
#2020
11
b1111 %
b1111 )
b1111 '
#2030
b10000 '
#2040
1"
0!
1/
00
16
1=
0;
08
15
1F
b0z ,
0D
07
b111z +
1>
b0z *
0@
0I
0A
09
01
1:
02
0-
b0 %
b0 )
b0 '
b1100 $
b1100 (
b1100 &
#2050
11
b1 %
b1 )
b1 '
#2060
19
01
b10 %
b10 )
b10 '
#2070
11
b11 %
b11 )
b11 '
#2080
1A
09
01
b100 %
b100 )
b100 '
#2090
11
b101 %
b101 )
b101 '
#2100
19
01
b110 %
b110 )
b110 '
#2110
11
b111 %
b111 )
b111 '
#2120
1"
1/
16
15
1>
0=
1;
b11z +
0F
b100z ,
1D
1I
0A
09
01
b1000 %
b1000 )
b1000 '
#2130
11
b1001 %
b1001 )
b1001 '
#2140
19
01
b1010 %
b1010 )
b1010 '
#2150
11
b1011 %
b1011 )
b1011 '
#2160
0"
1#
0/
1.
06
14
05
13
b0z +
0>
b111z ,
1<
1A
09
01
b1100 %
b1100 )
b1100 '
#2170
0#
1!
11
b1101 %
b1101 )
b1101 '
#2180
0.
10
b110z ,
04
0#
b1z *
18
1!
19
01
b1110 %
b1110 )
b1110 '
#2190
11
b1111 %
b1111 )
b1111 '
#2200
b10000 '
#2210
1"
1/
16
1=
0;
15
03
0!
0.
1F
0D
b111z +
1>
0<
00
b0z ,
04
b0z *
08
0I
0A
09
01
1-
b0 %
b0 )
b0 '
b1101 $
b1101 (
b1101 &
#2220
11
b1 %
b1 )
b1 '
#2230
19
01
b10 %
b10 )
b10 '
#2240
11
b11 %
b11 )
b11 '
#2250
1A
09
01
b100 %
b100 )
b100 '
#2260
11
b101 %
b101 )
b101 '
#2270
19
01
b110 %
b110 )
b110 '
#2280
11
b111 %
b111 )
b111 '
#2290
1"
1/
16
15
1>
0=
1;
b11z +
0F
b100z ,
1D
1I
0A
09
01
b1000 %
b1000 )
b1000 '
#2300
11
b1001 %
b1001 )
b1001 '
#2310
19
01
b1010 %
b1010 )
b1010 '
#2320
11
b1011 %
b1011 )
b1011 '
#2330
1"
0/
1.
06
14
05
13
b0z +
0>
b111z ,
1<
1A
09
01
b1100 %
b1100 )
b1100 '
#2340
0"
1#
11
b1101 %
b1101 )
b1101 '
#2350
1!
0.
10
b110z ,
04
0"
0#
b1z *
18
19
01
b1110 %
b1110 )
b1110 '
#2360
11
b1111 %
b1111 )
b1111 '
#2370
b10000 '
#2380
1"
1=
0;
15
03
0!
1/
1F
0D
1>
b0z ,
0<
00
b111z +
16
b0z *
08
0I
0A
09
01
12
0-
b0 %
b0 )
b0 '
b1110 $
b1110 (
b1110 &
#2390
11
b1 %
b1 )
b1 '
#2400
19
01
b10 %
b10 )
b10 '
#2410
11
b11 %
b11 )
b11 '
#2420
1A
09
01
b100 %
b100 )
b100 '
#2430
11
b101 %
b101 )
b101 '
#2440
19
01
b110 %
b110 )
b110 '
#2450
11
b111 %
b111 )
b111 '
#2460
1"
1/
16
15
1>
0=
1;
b11z +
0F
b100z ,
1D
1I
0A
09
01
b1000 %
b1000 )
b1000 '
#2470
11
b1001 %
b1001 )
b1001 '
#2480
19
01
b1010 %
b1010 )
b1010 '
#2490
11
b1011 %
b1011 )
b1011 '
#2500
1"
1/
16
05
13
b1z +
0>
b110z ,
1<
1A
09
01
b1100 %
b1100 )
b1100 '
#2510
11
b1101 %
b1101 )
b1101 '
#2520
0"
1#
0/
1.
b0z +
06
b111z ,
14
19
01
b1110 %
b1110 )
b1110 '
#2530
0#
1!
11
b1111 %
b1111 )
b1111 '
#2540
b10000 '
#2550
1=
0;
15
03
1/
0.
1F
0D
1>
0<
b111z +
16
b0z ,
04
1"
0!
0I
0A
09
01
1-
b0 %
b0 )
b0 '
b1111 $
b1111 (
b1111 &
#2560
11
b1 %
b1 )
b1 '
#2570
19
01
b10 %
b10 )
b10 '
#2580
11
b11 %
b11 )
b11 '
#2590
1A
09
01
b100 %
b100 )
b100 '
#2600
11
b101 %
b101 )
b101 '
#2610
19
01
b110 %
b110 )
b110 '
#2620
11
b111 %
b111 )
b111 '
#2630
1"
1/
16
15
1>
0=
1;
b11z +
0F
b100z ,
1D
1I
0A
09
01
b1000 %
b1000 )
b1000 '
#2640
11
b1001 %
b1001 )
b1001 '
#2650
19
01
b1010 %
b1010 )
b1010 '
#2660
11
b1011 %
b1011 )
b1011 '
#2670
1"
1/
16
05
13
b1z +
0>
b110z ,
1<
1A
09
01
b1100 %
b1100 )
b1100 '
#2680
11
b1101 %
b1101 )
b1101 '
#2690
1"
0/
1.
b0z +
06
b111z ,
14
19
01
b1110 %
b1110 )
b1110 '
#2700
0"
1#
11
b1111 %
b1111 )
b1111 '
#2710
b10000 '
#2720
b10000 &
